influx_si/C13_ftbl.py
influx_si/__init__.py
influx_si/cli.py
influx_si/influx_version.txt
influx_si/kvh.py
influx_si/licence_en.txt
influx_si/tools_ssg.py
influx_si/R/kvh.R
influx_si/R/libs.R
influx_si/R/load.R
influx_si/R/nlsic.R
influx_si/R/opt_cumo_tools.R
influx_si/R/opt_icumo_tools.R
influx_si/R/plot_imass.R
influx_si/R/plot_session.R
influx_si/R/plot_smeas.R
influx_si/R/preamble.R
influx_si/R/psoptim_ic.R
influx_si/R/save_all.R
influx_si/R/save_minenv.R
influx_si/R/test_psoptim_ic.R
influx_si/R/tools_ssg.R
influx_si/R/upd_deps.R
influx_si/doc/ChangeLog.pdf
influx_si/doc/FTBLSyntax.html
influx_si/doc/influx_si.pdf
influx_si/doc/html/changelog.html
influx_si/doc/html/consulting.html
influx_si/doc/html/genindex.html
influx_si/doc/html/howto.html
influx_si/doc/html/index.html
influx_si/doc/html/install.html
influx_si/doc/html/intro.html
influx_si/doc/html/license.html
influx_si/doc/html/manual.html
influx_si/doc/html/objects.inv
influx_si/doc/html/progdoc.html
influx_si/doc/html/py-modindex.html
influx_si/doc/html/quick.html
influx_si/doc/html/search.html
influx_si/doc/html/searchindex.js
influx_si/doc/html/trouble.html
influx_si/test/e_coli.ftbl
influx_si/test/e_coli_growth.ftbl
influx_si/test/e_coli_i.ftbl
influx_si/test/e_coli_msen.txt
influx_si/test/ok/e_coli.R
influx_si/test/ok/e_coli.err
influx_si/test/ok/e_coli.ftbl
influx_si/test/ok/e_coli.log
influx_si/test/ok/e_coli.pdf
influx_si/test/ok/e_coli.pres.csv
influx_si/test/ok/e_coli_growth.R
influx_si/test/ok/e_coli_growth.err
influx_si/test/ok/e_coli_growth.ftbl
influx_si/test/ok/e_coli_growth.log
influx_si/test/ok/e_coli_growth.pdf
influx_si/test/ok/e_coli_growth.pres.csv
influx_si/test/ok/e_coli_growth_res.kvh
influx_si/test/ok/e_coli_i.R
influx_si/test/ok/e_coli_i.err
influx_si/test/ok/e_coli_i.ftbl
influx_si/test/ok/e_coli_i.log
influx_si/test/ok/e_coli_i.pdf
influx_si/test/ok/e_coli_i.pres.csv
influx_si/test/ok/e_coli_i_res.kvh
influx_si/test/ok/e_coli_msen.txt
influx_si/test/ok/e_coli_res.kvh
influx_si-5.3.0.dist-info/METADATA
influx_si-5.3.0.dist-info/WHEEL
influx_si-5.3.0.dist-info/entry_points.txt
influx_si-5.3.0.dist-info/top_level.txt
influx_si-5.3.0.dist-info/RECORD
