Metadata-Version: 2.1
Name: influx-si
Version: 5.3.0
Summary: Metabolic flux and concentration estimation based on stable isotope labeling
Home-page: https://metasys.insa-toulouse.fr/software/influx/
Author: Serguei Sokol
Author-email: sokol@insa-toulouse.fr
License: GNU General Public License v2 or later (GPLv2+)
Project-URL: Documentation, https://metasys.insa-toulouse.fr/software/influx/doc/
Project-URL: Source, https://github.com/sgsokol/influx
Project-URL: Tracker, https://github.com/sgsokol/influx/issues
Keywords: metabolic flux analysis,least squares,isotope labeling,systems biology
Platform: UNKNOWN
Classifier: Environment :: Console
Classifier: Intended Audience :: End Users/Desktop
Classifier: License :: OSI Approved :: GNU General Public License v2 or later (GPLv2+)
Classifier: Operating System :: MacOS :: MacOS X
Classifier: Operating System :: Microsoft :: Windows
Classifier: Operating System :: POSIX
Classifier: Programming Language :: Python :: 3 :: Only
Classifier: Topic :: Scientific/Engineering :: Bio-Informatics
Requires-Dist: scipy
Requires-Dist: python-libsbml
